setup.py
lib/wc/__init__.py
lib/wc/web/__init__.py
lib/wc/web/hello.py
lib/wc_web.egg-info/PKG-INFO
lib/wc_web.egg-info/SOURCES.txt
lib/wc_web.egg-info/dependency_links.txt
lib/wc_web.egg-info/eager_resources.txt
lib/wc_web.egg-info/entry_points.txt
lib/wc_web.egg-info/namespace_packages.txt
lib/wc_web.egg-info/not-zip-safe
lib/wc_web.egg-info/requires.txt
lib/wc_web.egg-info/top_level.txt
scripts/runweb